{
  "availability" : {
    "CoreMotion" : {
      "CMAltimeter" : {
        "isRelativeAltitudeAvailable" : true
      },
      "CMMotionActivityManager" : {
        "isActivityAvailable" : true
      },
      "CMMotionManager" : {
        "isAccelerometerAvailable" : true,
        "isDeviceMotionAvailable" : true,
        "isGyroAvailable" : true,
        "isMagnetometerAvailable" : true
      },
      "CMPedometer" : {
        "isCadenceAvailable" : true,
        "isDistanceAvailable" : true,
        "isFloorCountingAvailable" : true,
        "isPaceAvailable" : true,
        "isPedometerEventTrackingAvailable" : true,
        "isStepCountingAvailable" : true
      },
      "CMSensorRecorder" : {
        "isAccelerometerRecordingAvailable" : true
      }
    }
  },
  "model" : "iPhone11,2",
  "name" : "iPhone XS"
}
